{
  "updated_at": "2026-04-23T10:54:11.644294+02:00",
  "updated_display": "23/04/2026 10:54 CET",
  "vix": null,
  "vstoxx": null,
  "regime": "NORMALE",
  "xeon_price": 148.9416,
  "portfolios": {
    "europa": {
      "name": "\ud83c\uddea\ud83c\uddfa EUROPA",
      "benchmark_label": "600X",
      "benchmark_price": 36.04,
      "benchmark_p30": 1.11,
      "regime": "NORMALE",
      "positions": [],
      "use_xeon": true,
      "cooldown": {
        "STZX.MI": "2026-04-22",
        "STKX.MI": "2026-04-23",
        "STPX.MI": "2026-04-23"
      },
      "watchlist": [
        {
          "ticker": "STNX.MI",
          "label": "STNX",
          "name": "SPDR MSCI Eu Energy",
          "price": 286.25,
          "sec_kama": 288.0021,
          "sec_above": false,
          "sar": 298.1072,
          "sar_bullish": false,
          "vi_plus": 0.8855,
          "vi_minus": 0.8895,
          "vortex_bullish": false,
          "rvi": -0.196869,
          "rvi_signal": -0.180073,
          "rvi_bullish": false,
          "rs": 7.942564,
          "rs_kama": 8.162877,
          "rs_above": false,
          "rs_kpct": -2.7,
          "rs_er": 0.1396,
          "rs_baff": 0,
          "rs_trend": "GRIGIO",
          "rs_cross": 12,
          "rs_rsi": 50.1,
          "rs_p7": 1.01,
          "rs_p30": 8.16,
          "rs_ao_pos": false,
          "rs_ao_improving": false,
          "kama_cross_up": false,
          "sec_er": 0.1312,
          "sec_trend": "VERDE",
          "score": 32.6,
          "signal": "EXIT3",
          "size": "0%",
          "qualifies": false
        },
        {
          "ticker": "STPX.MI",
          "label": "STPX",
          "name": "SPDR MSCI Eu Materials",
          "price": 366.4,
          "sec_kama": 365.4634,
          "sec_above": true,
          "sar": 360.74395,
          "sar_bullish": true,
          "vi_plus": 0.9031,
          "vi_minus": 0.8687,
          "vortex_bullish": true,
          "rvi": 0.115161,
          "rvi_signal": 0.005092,
          "rvi_bullish": true,
          "rs": 10.166481,
          "rs_kama": 10.013315,
          "rs_above": true,
          "rs_kpct": 1.53,
          "rs_er": 0.1794,
          "rs_baff": 0,
          "rs_trend": "VERDE",
          "rs_cross": 11,
          "rs_rsi": 58.1,
          "rs_p7": 0.53,
          "rs_p30": 5.96,
          "rs_ao_pos": true,
          "rs_ao_improving": false,
          "kama_cross_up": false,
          "sec_er": 0.2548,
          "sec_trend": "VERDE",
          "score": 29.0,
          "signal": "EXIT3",
          "size": "0%",
          "qualifies": false
        },
        {
          "ticker": "STZX.MI",
          "label": "STZX",
          "name": "SPDR MSCI Eu Financials",
          "price": 138.68,
          "sec_kama": 139.7323,
          "sec_above": false,
          "sar": 135.57994,
          "sar_bullish": true,
          "vi_plus": 0.9695,
          "vi_minus": 0.7382,
          "vortex_bullish": true,
          "rvi": 0.35642,
          "rvi_signal": 0.296357,
          "rvi_bullish": true,
          "rs": 3.847946,
          "rs_kama": 3.861294,
          "rs_above": false,
          "rs_kpct": -0.35,
          "rs_er": 0.1888,
          "rs_baff": 0,
          "rs_trend": "VERDE",
          "rs_cross": 1,
          "rs_rsi": 59.5,
          "rs_p7": 0.02,
          "rs_p30": 3.91,
          "rs_ao_pos": true,
          "rs_ao_improving": false,
          "kama_cross_up": false,
          "sec_er": 0.2075,
          "sec_trend": "VERDE",
          "score": 19.6,
          "signal": "EXIT3",
          "size": "0%",
          "qualifies": false
        },
        {
          "ticker": "STUX.MI",
          "label": "STUX",
          "name": "SPDR MSCI Eu Utilities",
          "price": 260.9,
          "sec_kama": 261.2408,
          "sec_above": false,
          "sar": 266.36361,
          "sar_bullish": false,
          "vi_plus": 0.9428,
          "vi_minus": 0.8956,
          "vortex_bullish": true,
          "rvi": -0.273662,
          "rvi_signal": -0.26348,
          "rvi_bullish": false,
          "rs": 7.239178,
          "rs_kama": 7.23783,
          "rs_above": true,
          "rs_kpct": 0.02,
          "rs_er": 0.2848,
          "rs_baff": 1,
          "rs_trend": "GRIGIO",
          "rs_cross": 1,
          "rs_rsi": 49.8,
          "rs_p7": -0.46,
          "rs_p30": 1.27,
          "rs_ao_pos": false,
          "rs_ao_improving": true,
          "kama_cross_up": false,
          "sec_er": 0.3314,
          "sec_trend": "VERDE",
          "score": 14.3,
          "signal": "EXIT3",
          "size": "0%",
          "qualifies": false
        },
        {
          "ticker": "STTX.MI",
          "label": "STTX",
          "name": "SPDR MSCI Eu Comm Services",
          "price": 75.75,
          "sec_kama": 76.7379,
          "sec_above": false,
          "sar": 74.68482,
          "sar_bullish": true,
          "vi_plus": 1.2111,
          "vi_minus": 1.4067,
          "vortex_bullish": false,
          "rvi": -1.653219,
          "rvi_signal": -1.84264,
          "rvi_bullish": true,
          "rs": 2.101831,
          "rs_kama": 2.168163,
          "rs_above": false,
          "rs_kpct": -3.06,
          "rs_er": 0.2667,
          "rs_baff": 0,
          "rs_trend": "GRIGIO",
          "rs_cross": 12,
          "rs_rsi": 42.5,
          "rs_p7": 0.3,
          "rs_p30": -4.16,
          "rs_ao_pos": false,
          "rs_ao_improving": false,
          "kama_cross_up": false,
          "sec_er": 0.3265,
          "sec_trend": "GRIGIO",
          "score": 10.1,
          "signal": "EXIT3",
          "size": "0%",
          "qualifies": false
        },
        {
          "ticker": "STSX.MI",
          "label": "STSX",
          "name": "SPDR MSCI Eu Cons Staples",
          "price": 225.75,
          "sec_kama": 224.4762,
          "sec_above": true,
          "sar": 227.41041,
          "sar_bullish": false,
          "vi_plus": 0.841,
          "vi_minus": 0.906,
          "vortex_bullish": false,
          "rvi": -0.330217,
          "rvi_signal": -0.459792,
          "rvi_bullish": true,
          "rs": 6.263873,
          "rs_kama": 6.262227,
          "rs_above": true,
          "rs_kpct": 0.03,
          "rs_er": 0.191,
          "rs_baff": 2,
          "rs_trend": "ROSSO",
          "rs_cross": 1,
          "rs_rsi": 44.0,
          "rs_p7": 0.9,
          "rs_p30": -4.68,
          "rs_ao_pos": false,
          "rs_ao_improving": true,
          "kama_cross_up": true,
          "sec_er": 0.0956,
          "sec_trend": "GRIGIO",
          "score": 6.0,
          "signal": "EXIT3",
          "size": "0%",
          "qualifies": false
        },
        {
          "ticker": "STQX.MI",
          "label": "STQX",
          "name": "SPDR MSCI Eu Industrials",
          "price": 431.35,
          "sec_kama": 429.054,
          "sec_above": true,
          "sar": 420.49328,
          "sar_bullish": true,
          "vi_plus": 0.8788,
          "vi_minus": 0.8412,
          "vortex_bullish": true,
          "rvi": 0.167956,
          "rvi_signal": 0.226465,
          "rvi_bullish": false,
          "rs": 11.968646,
          "rs_kama": 11.915653,
          "rs_above": true,
          "rs_kpct": 0.44,
          "rs_er": 0.0229,
          "rs_baff": 0,
          "rs_trend": "VERDE",
          "rs_cross": 12,
          "rs_rsi": 53.9,
          "rs_p7": -0.25,
          "rs_p30": -0.04,
          "rs_ao_pos": true,
          "rs_ao_improving": false,
          "kama_cross_up": false,
          "sec_er": 0.0965,
          "sec_trend": "VERDE",
          "score": 5.9,
          "signal": "EXIT3",
          "size": "0%",
          "qualifies": false
        },
        {
          "ticker": "STWX.MI",
          "label": "STWX",
          "name": "SPDR MSCI Eu Health Care",
          "price": 222.25,
          "sec_kama": 223.8884,
          "sec_above": false,
          "sar": 229.87896,
          "sar_bullish": false,
          "vi_plus": 0.8093,
          "vi_minus": 0.8918,
          "vortex_bullish": false,
          "rvi": -0.14306,
          "rvi_signal": -0.217189,
          "rvi_bullish": true,
          "rs": 6.166759,
          "rs_kama": 6.246053,
          "rs_above": false,
          "rs_kpct": -1.27,
          "rs_er": 0.6452,
          "rs_baff": 0,
          "rs_trend": "ROSSO",
          "rs_cross": 12,
          "rs_rsi": 32.0,
          "rs_p7": -1.71,
          "rs_p30": -3.72,
          "rs_ao_pos": false,
          "rs_ao_improving": false,
          "kama_cross_up": false,
          "sec_er": 0.1854,
          "sec_trend": "ROSSO",
          "score": 5.3,
          "signal": "EXIT3",
          "size": "0%",
          "qualifies": false
        }
      ],
      "qualified": [
        {
          "ticker": "STKX.MI",
          "label": "STKX",
          "name": "SPDR MSCI Eu Technology",
          "price": 173.98,
          "sec_kama": 170.9709,
          "sec_above": true,
          "sar": 164.84656,
          "sar_bullish": true,
          "vi_plus": 1.133,
          "vi_minus": 0.9036,
          "vortex_bullish": true,
          "rvi": 0.212457,
          "rvi_signal": 0.268495,
          "rvi_bullish": false,
          "rs": 4.827414,
          "rs_kama": 4.705976,
          "rs_above": true,
          "rs_kpct": 2.58,
          "rs_er": 0.7919,
          "rs_baff": 11,
          "rs_trend": "VERDE",
          "rs_cross": 11,
          "rs_rsi": 66.4,
          "rs_p7": 3.3,
          "rs_p30": 6.65,
          "rs_ao_pos": true,
          "rs_ao_improving": true,
          "kama_cross_up": false,
          "sec_er": 0.6649,
          "sec_trend": "VERDE",
          "score": 113.0,
          "signal": "BUY3",
          "size": "100%",
          "qualifies": true
        }
      ],
      "all": [
        {
          "ticker": "STKX.MI",
          "label": "STKX",
          "name": "SPDR MSCI Eu Technology",
          "price": 173.98,
          "sec_kama": 170.9709,
          "sec_above": true,
          "sar": 164.84656,
          "sar_bullish": true,
          "vi_plus": 1.133,
          "vi_minus": 0.9036,
          "vortex_bullish": true,
          "rvi": 0.212457,
          "rvi_signal": 0.268495,
          "rvi_bullish": false,
          "rs": 4.827414,
          "rs_kama": 4.705976,
          "rs_above": true,
          "rs_kpct": 2.58,
          "rs_er": 0.7919,
          "rs_baff": 11,
          "rs_trend": "VERDE",
          "rs_cross": 11,
          "rs_rsi": 66.4,
          "rs_p7": 3.3,
          "rs_p30": 6.65,
          "rs_ao_pos": true,
          "rs_ao_improving": true,
          "kama_cross_up": false,
          "sec_er": 0.6649,
          "sec_trend": "VERDE",
          "score": 113.0,
          "signal": "BUY3",
          "size": "100%",
          "qualifies": true
        },
        {
          "ticker": "STNX.MI",
          "label": "STNX",
          "name": "SPDR MSCI Eu Energy",
          "price": 286.25,
          "sec_kama": 288.0021,
          "sec_above": false,
          "sar": 298.1072,
          "sar_bullish": false,
          "vi_plus": 0.8855,
          "vi_minus": 0.8895,
          "vortex_bullish": false,
          "rvi": -0.196869,
          "rvi_signal": -0.180073,
          "rvi_bullish": false,
          "rs": 7.942564,
          "rs_kama": 8.162877,
          "rs_above": false,
          "rs_kpct": -2.7,
          "rs_er": 0.1396,
          "rs_baff": 0,
          "rs_trend": "GRIGIO",
          "rs_cross": 12,
          "rs_rsi": 50.1,
          "rs_p7": 1.01,
          "rs_p30": 8.16,
          "rs_ao_pos": false,
          "rs_ao_improving": false,
          "kama_cross_up": false,
          "sec_er": 0.1312,
          "sec_trend": "VERDE",
          "score": 32.6,
          "signal": "EXIT3",
          "size": "0%",
          "qualifies": false
        },
        {
          "ticker": "STPX.MI",
          "label": "STPX",
          "name": "SPDR MSCI Eu Materials",
          "price": 366.4,
          "sec_kama": 365.4634,
          "sec_above": true,
          "sar": 360.74395,
          "sar_bullish": true,
          "vi_plus": 0.9031,
          "vi_minus": 0.8687,
          "vortex_bullish": true,
          "rvi": 0.115161,
          "rvi_signal": 0.005092,
          "rvi_bullish": true,
          "rs": 10.166481,
          "rs_kama": 10.013315,
          "rs_above": true,
          "rs_kpct": 1.53,
          "rs_er": 0.1794,
          "rs_baff": 0,
          "rs_trend": "VERDE",
          "rs_cross": 11,
          "rs_rsi": 58.1,
          "rs_p7": 0.53,
          "rs_p30": 5.96,
          "rs_ao_pos": true,
          "rs_ao_improving": false,
          "kama_cross_up": false,
          "sec_er": 0.2548,
          "sec_trend": "VERDE",
          "score": 29.0,
          "signal": "EXIT3",
          "size": "0%",
          "qualifies": false
        },
        {
          "ticker": "STZX.MI",
          "label": "STZX",
          "name": "SPDR MSCI Eu Financials",
          "price": 138.68,
          "sec_kama": 139.7323,
          "sec_above": false,
          "sar": 135.57994,
          "sar_bullish": true,
          "vi_plus": 0.9695,
          "vi_minus": 0.7382,
          "vortex_bullish": true,
          "rvi": 0.35642,
          "rvi_signal": 0.296357,
          "rvi_bullish": true,
          "rs": 3.847946,
          "rs_kama": 3.861294,
          "rs_above": false,
          "rs_kpct": -0.35,
          "rs_er": 0.1888,
          "rs_baff": 0,
          "rs_trend": "VERDE",
          "rs_cross": 1,
          "rs_rsi": 59.5,
          "rs_p7": 0.02,
          "rs_p30": 3.91,
          "rs_ao_pos": true,
          "rs_ao_improving": false,
          "kama_cross_up": false,
          "sec_er": 0.2075,
          "sec_trend": "VERDE",
          "score": 19.6,
          "signal": "EXIT3",
          "size": "0%",
          "qualifies": false
        },
        {
          "ticker": "STUX.MI",
          "label": "STUX",
          "name": "SPDR MSCI Eu Utilities",
          "price": 260.9,
          "sec_kama": 261.2408,
          "sec_above": false,
          "sar": 266.36361,
          "sar_bullish": false,
          "vi_plus": 0.9428,
          "vi_minus": 0.8956,
          "vortex_bullish": true,
          "rvi": -0.273662,
          "rvi_signal": -0.26348,
          "rvi_bullish": false,
          "rs": 7.239178,
          "rs_kama": 7.23783,
          "rs_above": true,
          "rs_kpct": 0.02,
          "rs_er": 0.2848,
          "rs_baff": 1,
          "rs_trend": "GRIGIO",
          "rs_cross": 1,
          "rs_rsi": 49.8,
          "rs_p7": -0.46,
          "rs_p30": 1.27,
          "rs_ao_pos": false,
          "rs_ao_improving": true,
          "kama_cross_up": false,
          "sec_er": 0.3314,
          "sec_trend": "VERDE",
          "score": 14.3,
          "signal": "EXIT3",
          "size": "0%",
          "qualifies": false
        },
        {
          "ticker": "STTX.MI",
          "label": "STTX",
          "name": "SPDR MSCI Eu Comm Services",
          "price": 75.75,
          "sec_kama": 76.7379,
          "sec_above": false,
          "sar": 74.68482,
          "sar_bullish": true,
          "vi_plus": 1.2111,
          "vi_minus": 1.4067,
          "vortex_bullish": false,
          "rvi": -1.653219,
          "rvi_signal": -1.84264,
          "rvi_bullish": true,
          "rs": 2.101831,
          "rs_kama": 2.168163,
          "rs_above": false,
          "rs_kpct": -3.06,
          "rs_er": 0.2667,
          "rs_baff": 0,
          "rs_trend": "GRIGIO",
          "rs_cross": 12,
          "rs_rsi": 42.5,
          "rs_p7": 0.3,
          "rs_p30": -4.16,
          "rs_ao_pos": false,
          "rs_ao_improving": false,
          "kama_cross_up": false,
          "sec_er": 0.3265,
          "sec_trend": "GRIGIO",
          "score": 10.1,
          "signal": "EXIT3",
          "size": "0%",
          "qualifies": false
        },
        {
          "ticker": "STSX.MI",
          "label": "STSX",
          "name": "SPDR MSCI Eu Cons Staples",
          "price": 225.75,
          "sec_kama": 224.4762,
          "sec_above": true,
          "sar": 227.41041,
          "sar_bullish": false,
          "vi_plus": 0.841,
          "vi_minus": 0.906,
          "vortex_bullish": false,
          "rvi": -0.330217,
          "rvi_signal": -0.459792,
          "rvi_bullish": true,
          "rs": 6.263873,
          "rs_kama": 6.262227,
          "rs_above": true,
          "rs_kpct": 0.03,
          "rs_er": 0.191,
          "rs_baff": 2,
          "rs_trend": "ROSSO",
          "rs_cross": 1,
          "rs_rsi": 44.0,
          "rs_p7": 0.9,
          "rs_p30": -4.68,
          "rs_ao_pos": false,
          "rs_ao_improving": true,
          "kama_cross_up": true,
          "sec_er": 0.0956,
          "sec_trend": "GRIGIO",
          "score": 6.0,
          "signal": "EXIT3",
          "size": "0%",
          "qualifies": false
        },
        {
          "ticker": "STQX.MI",
          "label": "STQX",
          "name": "SPDR MSCI Eu Industrials",
          "price": 431.35,
          "sec_kama": 429.054,
          "sec_above": true,
          "sar": 420.49328,
          "sar_bullish": true,
          "vi_plus": 0.8788,
          "vi_minus": 0.8412,
          "vortex_bullish": true,
          "rvi": 0.167956,
          "rvi_signal": 0.226465,
          "rvi_bullish": false,
          "rs": 11.968646,
          "rs_kama": 11.915653,
          "rs_above": true,
          "rs_kpct": 0.44,
          "rs_er": 0.0229,
          "rs_baff": 0,
          "rs_trend": "VERDE",
          "rs_cross": 12,
          "rs_rsi": 53.9,
          "rs_p7": -0.25,
          "rs_p30": -0.04,
          "rs_ao_pos": true,
          "rs_ao_improving": false,
          "kama_cross_up": false,
          "sec_er": 0.0965,
          "sec_trend": "VERDE",
          "score": 5.9,
          "signal": "EXIT3",
          "size": "0%",
          "qualifies": false
        },
        {
          "ticker": "STWX.MI",
          "label": "STWX",
          "name": "SPDR MSCI Eu Health Care",
          "price": 222.25,
          "sec_kama": 223.8884,
          "sec_above": false,
          "sar": 229.87896,
          "sar_bullish": false,
          "vi_plus": 0.8093,
          "vi_minus": 0.8918,
          "vortex_bullish": false,
          "rvi": -0.14306,
          "rvi_signal": -0.217189,
          "rvi_bullish": true,
          "rs": 6.166759,
          "rs_kama": 6.246053,
          "rs_above": false,
          "rs_kpct": -1.27,
          "rs_er": 0.6452,
          "rs_baff": 0,
          "rs_trend": "ROSSO",
          "rs_cross": 12,
          "rs_rsi": 32.0,
          "rs_p7": -1.71,
          "rs_p30": -3.72,
          "rs_ao_pos": false,
          "rs_ao_improving": false,
          "kama_cross_up": false,
          "sec_er": 0.1854,
          "sec_trend": "ROSSO",
          "score": 5.3,
          "signal": "EXIT3",
          "size": "0%",
          "qualifies": false
        },
        {
          "ticker": "STRX.MI",
          "label": "STRX",
          "name": "SPDR MSCI Eu Cons Disc",
          "price": 151.24,
          "sec_kama": 150.3334,
          "sec_above": true,
          "sar": 148.48466,
          "sar_bullish": true,
          "vi_plus": 0.8762,
          "vi_minus": 0.8604,
          "vortex_bullish": true,
          "rvi": 0.370867,
          "rvi_signal": 0.382556,
          "rvi_bullish": false,
          "rs": 4.196448,
          "rs_kama": 4.268161,
          "rs_above": false,
          "rs_kpct": -1.68,
          "rs_er": 0.0995,
          "rs_baff": 0,
          "rs_trend": "ROSSO",
          "rs_cross": 2,
          "rs_rsi": 44.0,
          "rs_p7": -0.48,
          "rs_p30": -3.36,
          "rs_ao_pos": false,
          "rs_ao_improving": false,
          "kama_cross_up": false,
          "sec_er": 0.0055,
          "sec_trend": "ROSSO",
          "score": -0.4,
          "signal": "EXIT3",
          "size": "0%",
          "qualifies": false
        },
        {
          "ticker": "DFSV.DE",
          "label": "DFSV",
          "name": "SPDR S&P Eu Defence",
          "price": 10.23,
          "sec_kama": 10.5927,
          "sec_above": false,
          "sar": 11.14,
          "sar_bullish": false,
          "vi_plus": 0.7781,
          "vi_minus": 1.1444,
          "vortex_bullish": false,
          "rvi": -0.222833,
          "rvi_signal": -0.11708,
          "rvi_bullish": false,
          "rs": 0.283851,
          "rs_kama": 0.29654,
          "rs_above": false,
          "rs_kpct": -4.28,
          "rs_er": 0.5674,
          "rs_baff": 0,
          "rs_trend": "ROSSO",
          "rs_cross": 10,
          "rs_rsi": 33.9,
          "rs_p7": -5.5,
          "rs_p30": -11.08,
          "rs_ao_pos": false,
          "rs_ao_improving": false,
          "kama_cross_up": false,
          "sec_er": 0.4745,
          "sec_trend": "ROSSO",
          "score": -8.6,
          "signal": "EXIT3",
          "size": "0%",
          "qualifies": false
        }
      ],
      "buy3_count": 1,
      "buy2_count": 0,
      "buy1_count": 0
    },
    "usa": {
      "name": "\ud83c\uddfa\ud83c\uddf8 USA",
      "benchmark_label": "SP5A",
      "benchmark_price": 14.982,
      "benchmark_p30": 3.87,
      "regime": "NORMALE",
      "positions": [
        {
          "ticker": "SXLK.MI",
          "label": "SXLK",
          "name": "SPDR S&P US Technology",
          "entry_date": "2026-04-20",
          "entry_price": 136.21,
          "current_price": 139.02,
          "target_price": 143.0205,
          "current_gain_pct": 2.06,
          "days_held": 3,
          "pre_alert": false,
          "target_hit": false,
          "pre_rs_alert": false,
          "signal": "BUY3",
          "size": "100%",
          "score": 115.0,
          "rs_er": 0.9462,
          "rs_trend": "VERDE",
          "rs_baff": 14,
          "rs_kpct": 0.99,
          "rs_above": true,
          "sec_above": true,
          "sec_er": 0.9194,
          "sar_bullish": true,
          "vortex_bullish": true,
          "rvi_bullish": true,
          "weight_pct": 100.0,
          "warning": null
        }
      ],
      "use_xeon": false,
      "cooldown": {
        "SXLY.MI": "2026-04-22"
      },
      "watchlist": [
        {
          "ticker": "SXLY.MI",
          "label": "SXLY",
          "name": "SPDR S&P US Cons Disc",
          "price": 62.5,
          "sec_kama": 61.8796,
          "sec_above": true,
          "sar": 60.03331,
          "sar_bullish": true,
          "vi_plus": 1.0591,
          "vi_minus": 0.7352,
          "vortex_bullish": true,
          "rvi": 0.514768,
          "rvi_signal": 0.436772,
          "rvi_bullish": true,
          "rs": 4.171673,
          "rs_kama": 4.186934,
          "rs_above": false,
          "rs_kpct": -0.36,
          "rs_er": 0.2243,
          "rs_baff": 0,
          "rs_trend": "GRIGIO",
          "rs_cross": 1,
          "rs_rsi": 50.6,
          "rs_p7": -0.39,
          "rs_p30": 0.22,
          "rs_ao_pos": true,
          "rs_ao_improving": false,
          "kama_cross_up": false,
          "sec_er": 0.5565,
          "sec_trend": "VERDE",
          "score": 11.7,
          "signal": "EXIT3",
          "size": "0%",
          "qualifies": false
        },
        {
          "ticker": "SXLP.MI",
          "label": "SXLP",
          "name": "SPDR S&P US Cons Staples",
          "price": 38.66,
          "sec_kama": 38.8141,
          "sec_above": false,
          "sar": 39.10058,
          "sar_bullish": false,
          "vi_plus": 1.051,
          "vi_minus": 1.0581,
          "vortex_bullish": false,
          "rvi": -0.327262,
          "rvi_signal": -0.421136,
          "rvi_bullish": true,
          "rs": 2.58043,
          "rs_kama": 2.609109,
          "rs_above": false,
          "rs_kpct": -1.1,
          "rs_er": 0.6265,
          "rs_baff": 3,
          "rs_trend": "ROSSO",
          "rs_cross": 15,
          "rs_rsi": 35.1,
          "rs_p7": -0.93,
          "rs_p30": -7.25,
          "rs_ao_pos": false,
          "rs_ao_improving": true,
          "kama_cross_up": false,
          "sec_er": 0.1481,
          "sec_trend": "GRIGIO",
          "score": 11.3,
          "signal": "EXIT3",
          "size": "0%",
          "qualifies": false
        },
        {
          "ticker": "SXLE.MI",
          "label": "SXLE",
          "name": "SPDR S&P US Energy",
          "price": 38.88,
          "sec_kama": 39.7053,
          "sec_above": false,
          "sar": 40.70345,
          "sar_bullish": false,
          "vi_plus": 0.8735,
          "vi_minus": 0.9209,
          "vortex_bullish": false,
          "rvi": -0.314217,
          "rvi_signal": -0.31873,
          "rvi_bullish": true,
          "rs": 2.595114,
          "rs_kama": 2.678334,
          "rs_above": false,
          "rs_kpct": -3.11,
          "rs_er": 0.3637,
          "rs_baff": 0,
          "rs_trend": "GRIGIO",
          "rs_cross": 15,
          "rs_rsi": 42.0,
          "rs_p7": -1.0,
          "rs_p30": -2.52,
          "rs_ao_pos": false,
          "rs_ao_improving": false,
          "kama_cross_up": false,
          "sec_er": 0.1545,
          "sec_trend": "GRIGIO",
          "score": 11.2,
          "signal": "EXIT3",
          "size": "0%",
          "qualifies": false
        },
        {
          "ticker": "SXLB.MI",
          "label": "SXLB",
          "name": "SPDR S&P US Materials",
          "price": 44.125,
          "sec_kama": 43.7773,
          "sec_above": true,
          "sar": 43.9026,
          "sar_bullish": true,
          "vi_plus": 0.9971,
          "vi_minus": 0.7351,
          "vortex_bullish": true,
          "rvi": 0.064287,
          "rvi_signal": -0.027476,
          "rvi_bullish": true,
          "rs": 2.945201,
          "rs_kama": 2.981232,
          "rs_above": false,
          "rs_kpct": -1.21,
          "rs_er": 0.7359,
          "rs_baff": 0,
          "rs_trend": "GRIGIO",
          "rs_cross": 8,
          "rs_rsi": 38.0,
          "rs_p7": -3.23,
          "rs_p30": -1.04,
          "rs_ao_pos": false,
          "rs_ao_improving": false,
          "kama_cross_up": false,
          "sec_er": 0.0385,
          "sec_trend": "VERDE",
          "score": 10.7,
          "signal": "EXIT3",
          "size": "0%",
          "qualifies": false
        },
        {
          "ticker": "SXLF.MI",
          "label": "SXLF",
          "name": "SPDR S&P US Financials",
          "price": 52.77,
          "sec_kama": 52.4384,
          "sec_above": true,
          "sar": 51.97497,
          "sar_bullish": true,
          "vi_plus": 1.1676,
          "vi_minus": 0.8994,
          "vortex_bullish": true,
          "rvi": 0.162142,
          "rvi_signal": 0.155597,
          "rvi_bullish": true,
          "rs": 3.522227,
          "rs_kama": 3.567236,
          "rs_above": false,
          "rs_kpct": -1.26,
          "rs_er": 0.6022,
          "rs_baff": 0,
          "rs_trend": "ROSSO",
          "rs_cross": 12,
          "rs_rsi": 38.5,
          "rs_p7": -1.73,
          "rs_p30": -0.27,
          "rs_ao_pos": false,
          "rs_ao_improving": false,
          "kama_cross_up": false,
          "sec_er": 0.4274,
          "sec_trend": "GRIGIO",
          "score": 8.6,
          "signal": "EXIT3",
          "size": "0%",
          "qualifies": false
        },
        {
          "ticker": "MGIN.MI",
          "label": "MGIN",
          "name": "SPDR Morningstar Multi-Asset Global Infra",
          "price": 32.75,
          "sec_kama": 32.7691,
          "sec_above": false,
          "sar": 32.8654,
          "sar_bullish": false,
          "vi_plus": 0.9538,
          "vi_minus": 1.01,
          "vortex_bullish": false,
          "rvi": -0.493501,
          "rvi_signal": -0.621799,
          "rvi_bullish": true,
          "rs": 2.185956,
          "rs_kama": 2.20279,
          "rs_above": false,
          "rs_kpct": -0.76,
          "rs_er": 0.79,
          "rs_baff": 0,
          "rs_trend": "ROSSO",
          "rs_cross": 12,
          "rs_rsi": 29.8,
          "rs_p7": -2.89,
          "rs_p30": -4.41,
          "rs_ao_pos": false,
          "rs_ao_improving": false,
          "kama_cross_up": false,
          "sec_er": 0.2889,
          "sec_trend": "VERDE",
          "score": 3.4,
          "signal": "EXIT3",
          "size": "0%",
          "qualifies": false
        },
        {
          "ticker": "SXLI.MI",
          "label": "SXLI",
          "name": "SPDR S&P US Industrials",
          "price": 63.47,
          "sec_kama": 62.728,
          "sec_above": true,
          "sar": 63.32001,
          "sar_bullish": true,
          "vi_plus": 1.0425,
          "vi_minus": 0.724,
          "vortex_bullish": true,
          "rvi": 0.05406,
          "rvi_signal": 0.039256,
          "rvi_bullish": true,
          "rs": 4.236417,
          "rs_kama": 4.300294,
          "rs_above": false,
          "rs_kpct": -1.49,
          "rs_er": 0.7532,
          "rs_baff": 0,
          "rs_trend": "ROSSO",
          "rs_cross": 7,
          "rs_rsi": 33.3,
          "rs_p7": -3.9,
          "rs_p30": -4.0,
          "rs_ao_pos": false,
          "rs_ao_improving": false,
          "kama_cross_up": false,
          "sec_er": 0.0094,
          "sec_trend": "VERDE",
          "score": 2.1,
          "signal": "EXIT3",
          "size": "0%",
          "qualifies": false
        },
        {
          "ticker": "SXLC.MI",
          "label": "SXLC",
          "name": "SPDR S&P US Comm Services",
          "price": 47.18,
          "sec_kama": 47.1406,
          "sec_above": true,
          "sar": 46.0261,
          "sar_bullish": true,
          "vi_plus": 1.1575,
          "vi_minus": 0.8143,
          "vortex_bullish": true,
          "rvi": 0.122185,
          "rvi_signal": 0.152762,
          "rvi_bullish": false,
          "rs": 3.149112,
          "rs_kama": 3.192823,
          "rs_above": false,
          "rs_kpct": -1.37,
          "rs_er": 0.3331,
          "rs_baff": 0,
          "rs_trend": "GRIGIO",
          "rs_cross": 5,
          "rs_rsi": 41.7,
          "rs_p7": -2.46,
          "rs_p30": -2.68,
          "rs_ao_pos": false,
          "rs_ao_improving": false,
          "kama_cross_up": true,
          "sec_er": 0.4256,
          "sec_trend": "VERDE",
          "score": -1.1,
          "signal": "EXIT3",
          "size": "0%",
          "qualifies": false
        }
      ],
      "qualified": [
        {
          "ticker": "SXLK.MI",
          "label": "SXLK",
          "name": "SPDR S&P US Technology",
          "price": 139.02,
          "sec_kama": 137.115,
          "sec_above": true,
          "sar": 128.97167,
          "sar_bullish": true,
          "vi_plus": 1.3281,
          "vi_minus": 0.4794,
          "vortex_bullish": true,
          "rvi": 0.567547,
          "rvi_signal": 0.435803,
          "rvi_bullish": true,
          "rs": 9.279135,
          "rs_kama": 9.187831,
          "rs_above": true,
          "rs_kpct": 0.99,
          "rs_er": 0.9462,
          "rs_baff": 14,
          "rs_trend": "VERDE",
          "rs_cross": 12,
          "rs_rsi": 74.4,
          "rs_p7": 4.36,
          "rs_p30": 5.6,
          "rs_ao_pos": true,
          "rs_ao_improving": true,
          "kama_cross_up": false,
          "sec_er": 0.9194,
          "sec_trend": "VERDE",
          "score": 115.0,
          "signal": "BUY3",
          "size": "100%",
          "qualifies": true
        }
      ],
      "all": [
        {
          "ticker": "SXLK.MI",
          "label": "SXLK",
          "name": "SPDR S&P US Technology",
          "price": 139.02,
          "sec_kama": 137.115,
          "sec_above": true,
          "sar": 128.97167,
          "sar_bullish": true,
          "vi_plus": 1.3281,
          "vi_minus": 0.4794,
          "vortex_bullish": true,
          "rvi": 0.567547,
          "rvi_signal": 0.435803,
          "rvi_bullish": true,
          "rs": 9.279135,
          "rs_kama": 9.187831,
          "rs_above": true,
          "rs_kpct": 0.99,
          "rs_er": 0.9462,
          "rs_baff": 14,
          "rs_trend": "VERDE",
          "rs_cross": 12,
          "rs_rsi": 74.4,
          "rs_p7": 4.36,
          "rs_p30": 5.6,
          "rs_ao_pos": true,
          "rs_ao_improving": true,
          "kama_cross_up": false,
          "sec_er": 0.9194,
          "sec_trend": "VERDE",
          "score": 115.0,
          "signal": "BUY3",
          "size": "100%",
          "qualifies": true
        },
        {
          "ticker": "SXLY.MI",
          "label": "SXLY",
          "name": "SPDR S&P US Cons Disc",
          "price": 62.5,
          "sec_kama": 61.8796,
          "sec_above": true,
          "sar": 60.03331,
          "sar_bullish": true,
          "vi_plus": 1.0591,
          "vi_minus": 0.7352,
          "vortex_bullish": true,
          "rvi": 0.514768,
          "rvi_signal": 0.436772,
          "rvi_bullish": true,
          "rs": 4.171673,
          "rs_kama": 4.186934,
          "rs_above": false,
          "rs_kpct": -0.36,
          "rs_er": 0.2243,
          "rs_baff": 0,
          "rs_trend": "GRIGIO",
          "rs_cross": 1,
          "rs_rsi": 50.6,
          "rs_p7": -0.39,
          "rs_p30": 0.22,
          "rs_ao_pos": true,
          "rs_ao_improving": false,
          "kama_cross_up": false,
          "sec_er": 0.5565,
          "sec_trend": "VERDE",
          "score": 11.7,
          "signal": "EXIT3",
          "size": "0%",
          "qualifies": false
        },
        {
          "ticker": "SXLP.MI",
          "label": "SXLP",
          "name": "SPDR S&P US Cons Staples",
          "price": 38.66,
          "sec_kama": 38.8141,
          "sec_above": false,
          "sar": 39.10058,
          "sar_bullish": false,
          "vi_plus": 1.051,
          "vi_minus": 1.0581,
          "vortex_bullish": false,
          "rvi": -0.327262,
          "rvi_signal": -0.421136,
          "rvi_bullish": true,
          "rs": 2.58043,
          "rs_kama": 2.609109,
          "rs_above": false,
          "rs_kpct": -1.1,
          "rs_er": 0.6265,
          "rs_baff": 3,
          "rs_trend": "ROSSO",
          "rs_cross": 15,
          "rs_rsi": 35.1,
          "rs_p7": -0.93,
          "rs_p30": -7.25,
          "rs_ao_pos": false,
          "rs_ao_improving": true,
          "kama_cross_up": false,
          "sec_er": 0.1481,
          "sec_trend": "GRIGIO",
          "score": 11.3,
          "signal": "EXIT3",
          "size": "0%",
          "qualifies": false
        },
        {
          "ticker": "SXLE.MI",
          "label": "SXLE",
          "name": "SPDR S&P US Energy",
          "price": 38.88,
          "sec_kama": 39.7053,
          "sec_above": false,
          "sar": 40.70345,
          "sar_bullish": false,
          "vi_plus": 0.8735,
          "vi_minus": 0.9209,
          "vortex_bullish": false,
          "rvi": -0.314217,
          "rvi_signal": -0.31873,
          "rvi_bullish": true,
          "rs": 2.595114,
          "rs_kama": 2.678334,
          "rs_above": false,
          "rs_kpct": -3.11,
          "rs_er": 0.3637,
          "rs_baff": 0,
          "rs_trend": "GRIGIO",
          "rs_cross": 15,
          "rs_rsi": 42.0,
          "rs_p7": -1.0,
          "rs_p30": -2.52,
          "rs_ao_pos": false,
          "rs_ao_improving": false,
          "kama_cross_up": false,
          "sec_er": 0.1545,
          "sec_trend": "GRIGIO",
          "score": 11.2,
          "signal": "EXIT3",
          "size": "0%",
          "qualifies": false
        },
        {
          "ticker": "SXLB.MI",
          "label": "SXLB",
          "name": "SPDR S&P US Materials",
          "price": 44.125,
          "sec_kama": 43.7773,
          "sec_above": true,
          "sar": 43.9026,
          "sar_bullish": true,
          "vi_plus": 0.9971,
          "vi_minus": 0.7351,
          "vortex_bullish": true,
          "rvi": 0.064287,
          "rvi_signal": -0.027476,
          "rvi_bullish": true,
          "rs": 2.945201,
          "rs_kama": 2.981232,
          "rs_above": false,
          "rs_kpct": -1.21,
          "rs_er": 0.7359,
          "rs_baff": 0,
          "rs_trend": "GRIGIO",
          "rs_cross": 8,
          "rs_rsi": 38.0,
          "rs_p7": -3.23,
          "rs_p30": -1.04,
          "rs_ao_pos": false,
          "rs_ao_improving": false,
          "kama_cross_up": false,
          "sec_er": 0.0385,
          "sec_trend": "VERDE",
          "score": 10.7,
          "signal": "EXIT3",
          "size": "0%",
          "qualifies": false
        },
        {
          "ticker": "SXLF.MI",
          "label": "SXLF",
          "name": "SPDR S&P US Financials",
          "price": 52.77,
          "sec_kama": 52.4384,
          "sec_above": true,
          "sar": 51.97497,
          "sar_bullish": true,
          "vi_plus": 1.1676,
          "vi_minus": 0.8994,
          "vortex_bullish": true,
          "rvi": 0.162142,
          "rvi_signal": 0.155597,
          "rvi_bullish": true,
          "rs": 3.522227,
          "rs_kama": 3.567236,
          "rs_above": false,
          "rs_kpct": -1.26,
          "rs_er": 0.6022,
          "rs_baff": 0,
          "rs_trend": "ROSSO",
          "rs_cross": 12,
          "rs_rsi": 38.5,
          "rs_p7": -1.73,
          "rs_p30": -0.27,
          "rs_ao_pos": false,
          "rs_ao_improving": false,
          "kama_cross_up": false,
          "sec_er": 0.4274,
          "sec_trend": "GRIGIO",
          "score": 8.6,
          "signal": "EXIT3",
          "size": "0%",
          "qualifies": false
        },
        {
          "ticker": "MGIN.MI",
          "label": "MGIN",
          "name": "SPDR Morningstar Multi-Asset Global Infra",
          "price": 32.75,
          "sec_kama": 32.7691,
          "sec_above": false,
          "sar": 32.8654,
          "sar_bullish": false,
          "vi_plus": 0.9538,
          "vi_minus": 1.01,
          "vortex_bullish": false,
          "rvi": -0.493501,
          "rvi_signal": -0.621799,
          "rvi_bullish": true,
          "rs": 2.185956,
          "rs_kama": 2.20279,
          "rs_above": false,
          "rs_kpct": -0.76,
          "rs_er": 0.79,
          "rs_baff": 0,
          "rs_trend": "ROSSO",
          "rs_cross": 12,
          "rs_rsi": 29.8,
          "rs_p7": -2.89,
          "rs_p30": -4.41,
          "rs_ao_pos": false,
          "rs_ao_improving": false,
          "kama_cross_up": false,
          "sec_er": 0.2889,
          "sec_trend": "VERDE",
          "score": 3.4,
          "signal": "EXIT3",
          "size": "0%",
          "qualifies": false
        },
        {
          "ticker": "SXLI.MI",
          "label": "SXLI",
          "name": "SPDR S&P US Industrials",
          "price": 63.47,
          "sec_kama": 62.728,
          "sec_above": true,
          "sar": 63.32001,
          "sar_bullish": true,
          "vi_plus": 1.0425,
          "vi_minus": 0.724,
          "vortex_bullish": true,
          "rvi": 0.05406,
          "rvi_signal": 0.039256,
          "rvi_bullish": true,
          "rs": 4.236417,
          "rs_kama": 4.300294,
          "rs_above": false,
          "rs_kpct": -1.49,
          "rs_er": 0.7532,
          "rs_baff": 0,
          "rs_trend": "ROSSO",
          "rs_cross": 7,
          "rs_rsi": 33.3,
          "rs_p7": -3.9,
          "rs_p30": -4.0,
          "rs_ao_pos": false,
          "rs_ao_improving": false,
          "kama_cross_up": false,
          "sec_er": 0.0094,
          "sec_trend": "VERDE",
          "score": 2.1,
          "signal": "EXIT3",
          "size": "0%",
          "qualifies": false
        },
        {
          "ticker": "SXLC.MI",
          "label": "SXLC",
          "name": "SPDR S&P US Comm Services",
          "price": 47.18,
          "sec_kama": 47.1406,
          "sec_above": true,
          "sar": 46.0261,
          "sar_bullish": true,
          "vi_plus": 1.1575,
          "vi_minus": 0.8143,
          "vortex_bullish": true,
          "rvi": 0.122185,
          "rvi_signal": 0.152762,
          "rvi_bullish": false,
          "rs": 3.149112,
          "rs_kama": 3.192823,
          "rs_above": false,
          "rs_kpct": -1.37,
          "rs_er": 0.3331,
          "rs_baff": 0,
          "rs_trend": "GRIGIO",
          "rs_cross": 5,
          "rs_rsi": 41.7,
          "rs_p7": -2.46,
          "rs_p30": -2.68,
          "rs_ao_pos": false,
          "rs_ao_improving": false,
          "kama_cross_up": true,
          "sec_er": 0.4256,
          "sec_trend": "VERDE",
          "score": -1.1,
          "signal": "EXIT3",
          "size": "0%",
          "qualifies": false
        },
        {
          "ticker": "SXLV.MI",
          "label": "SXLV",
          "name": "SPDR S&P US Health Care",
          "price": 38.74,
          "sec_kama": 39.1317,
          "sec_above": false,
          "sar": 39.35029,
          "sar_bullish": false,
          "vi_plus": 0.8842,
          "vi_minus": 1.0652,
          "vortex_bullish": false,
          "rvi": -0.217372,
          "rvi_signal": -0.246733,
          "rvi_bullish": true,
          "rs": 2.58577,
          "rs_kama": 2.603322,
          "rs_above": false,
          "rs_kpct": -0.67,
          "rs_er": 0.8653,
          "rs_baff": 1,
          "rs_trend": "ROSSO",
          "rs_cross": 13,
          "rs_rsi": 20.2,
          "rs_p7": -4.39,
          "rs_p30": -8.67,
          "rs_ao_pos": false,
          "rs_ao_improving": true,
          "kama_cross_up": false,
          "sec_er": 0.25,
          "sec_trend": "ROSSO",
          "score": -1.2,
          "signal": "EXIT3",
          "size": "0%",
          "qualifies": false
        },
        {
          "ticker": "SXLU.MI",
          "label": "SXLU",
          "name": "SPDR S&P US Utilities",
          "price": 48.375,
          "sec_kama": 49.5091,
          "sec_above": false,
          "sar": 51.22094,
          "sar_bullish": false,
          "vi_plus": 0.8109,
          "vi_minus": 0.9364,
          "vortex_bullish": false,
          "rvi": -0.321521,
          "rvi_signal": -0.370425,
          "rvi_bullish": true,
          "rs": 3.228875,
          "rs_kama": 3.327336,
          "rs_above": false,
          "rs_kpct": -2.96,
          "rs_er": 0.7674,
          "rs_baff": 0,
          "rs_trend": "ROSSO",
          "rs_cross": 9,
          "rs_rsi": 33.4,
          "rs_p7": -5.3,
          "rs_p30": -7.41,
          "rs_ao_pos": false,
          "rs_ao_improving": false,
          "kama_cross_up": false,
          "sec_er": 0.5867,
          "sec_trend": "GRIGIO",
          "score": -2.5,
          "signal": "EXIT3",
          "size": "0%",
          "qualifies": false
        }
      ],
      "buy3_count": 1,
      "buy2_count": 0,
      "buy1_count": 0
    },
    "mondo": {
      "name": "\ud83c\udf0d MONDO",
      "benchmark_label": "SWRD",
      "benchmark_price": 42.565,
      "benchmark_p30": 3.05,
      "regime": "NORMALE",
      "positions": [
        {
          "ticker": "WTEC.MI",
          "label": "WTEC",
          "name": "SPDR MSCI Wld Technology",
          "entry_date": "2026-04-20",
          "entry_price": 196.24,
          "current_price": 199.97,
          "target_price": 206.052,
          "current_gain_pct": 1.9,
          "days_held": 3,
          "pre_alert": false,
          "target_hit": false,
          "pre_rs_alert": false,
          "signal": "BUY3",
          "size": "100%",
          "score": 119.9,
          "rs_er": 1.0,
          "rs_trend": "VERDE",
          "rs_baff": 13,
          "rs_kpct": 0.92,
          "rs_above": true,
          "sec_above": true,
          "sec_er": 0.9494,
          "sar_bullish": true,
          "vortex_bullish": true,
          "rvi_bullish": true,
          "weight_pct": 100.0,
          "warning": null
        }
      ],
      "use_xeon": false,
      "cooldown": {
        "WCOD.MI": "2026-04-22"
      },
      "watchlist": [
        {
          "ticker": "WTEL.MI",
          "label": "WTEL",
          "name": "SPDR MSCI Wld Comm Services",
          "price": 71.5,
          "sec_kama": 71.3685,
          "sec_above": true,
          "sar": 68.78781,
          "sar_bullish": true,
          "vi_plus": 1.3782,
          "vi_minus": 1.2496,
          "vortex_bullish": true,
          "rvi": 1.381731,
          "rvi_signal": 1.610676,
          "rvi_bullish": false,
          "rs": 1.679784,
          "rs_kama": 1.669535,
          "rs_above": true,
          "rs_kpct": 0.61,
          "rs_er": 0.1684,
          "rs_baff": 0,
          "rs_trend": "GRIGIO",
          "rs_cross": 7,
          "rs_rsi": 51.8,
          "rs_p7": 1.48,
          "rs_p30": 0.28,
          "rs_ao_pos": true,
          "rs_ao_improving": false,
          "kama_cross_up": false,
          "sec_er": 0.8177,
          "sec_trend": "VERDE",
          "score": 18.4,
          "signal": "EXIT3",
          "size": "0%",
          "qualifies": false
        },
        {
          "ticker": "WMAT.MI",
          "label": "WMAT",
          "name": "SPDR MSCI Wld Materials",
          "price": 71.65,
          "sec_kama": 71.1188,
          "sec_above": true,
          "sar": 70.67405,
          "sar_bullish": true,
          "vi_plus": 0.7974,
          "vi_minus": 0.6919,
          "vortex_bullish": true,
          "rvi": 0.17771,
          "rvi_signal": 0.084579,
          "rvi_bullish": true,
          "rs": 1.683308,
          "rs_kama": 1.694585,
          "rs_above": false,
          "rs_kpct": -0.67,
          "rs_er": 0.2466,
          "rs_baff": 1,
          "rs_trend": "GRIGIO",
          "rs_cross": 2,
          "rs_rsi": 48.3,
          "rs_p7": -1.68,
          "rs_p30": 2.25,
          "rs_ao_pos": true,
          "rs_ao_improving": true,
          "kama_cross_up": false,
          "sec_er": 0.1353,
          "sec_trend": "VERDE",
          "score": 17.2,
          "signal": "EXIT3",
          "size": "0%",
          "qualifies": false
        },
        {
          "ticker": "WNRG.MI",
          "label": "WNRG",
          "name": "SPDR MSCI Wld Energy",
          "price": 61.1,
          "sec_kama": 62.2981,
          "sec_above": false,
          "sar": 62.89003,
          "sar_bullish": false,
          "vi_plus": 0.8525,
          "vi_minus": 0.9022,
          "vortex_bullish": false,
          "rvi": -0.367062,
          "rvi_signal": -0.339138,
          "rvi_bullish": false,
          "rs": 1.435452,
          "rs_kama": 1.479389,
          "rs_above": false,
          "rs_kpct": -2.97,
          "rs_er": 0.3346,
          "rs_baff": 0,
          "rs_trend": "GRIGIO",
          "rs_cross": 15,
          "rs_rsi": 43.8,
          "rs_p7": -0.92,
          "rs_p30": -0.72,
          "rs_ao_pos": false,
          "rs_ao_improving": false,
          "kama_cross_up": false,
          "sec_er": 0.1729,
          "sec_trend": "GRIGIO",
          "score": 13.8,
          "signal": "EXIT3",
          "size": "0%",
          "qualifies": false
        },
        {
          "ticker": "WFIN.MI",
          "label": "WFIN",
          "name": "SPDR MSCI Wld Financials",
          "price": 80.17,
          "sec_kama": 80.2131,
          "sec_above": false,
          "sar": 78.45473,
          "sar_bullish": true,
          "vi_plus": 1.1729,
          "vi_minus": 1.0404,
          "vortex_bullish": true,
          "rvi": 0.161927,
          "rvi_signal": 0.298476,
          "rvi_bullish": false,
          "rs": 1.883472,
          "rs_kama": 1.905032,
          "rs_above": false,
          "rs_kpct": -1.13,
          "rs_er": 0.255,
          "rs_baff": 0,
          "rs_trend": "ROSSO",
          "rs_cross": 3,
          "rs_rsi": 47.8,
          "rs_p7": -0.35,
          "rs_p30": 2.65,
          "rs_ao_pos": true,
          "rs_ao_improving": false,
          "kama_cross_up": false,
          "sec_er": 0.3896,
          "sec_trend": "VERDE",
          "score": 12.0,
          "signal": "EXIT3",
          "size": "0%",
          "qualifies": false
        },
        {
          "ticker": "WCOS.MI",
          "label": "WCOS",
          "name": "SPDR MSCI Wld Cons Staples",
          "price": 45.535,
          "sec_kama": 45.9778,
          "sec_above": false,
          "sar": 46.28056,
          "sar_bullish": false,
          "vi_plus": 1.0824,
          "vi_minus": 1.5795,
          "vortex_bullish": false,
          "rvi": -1.175051,
          "rvi_signal": -1.300747,
          "rvi_bullish": true,
          "rs": 1.069776,
          "rs_kama": 1.089366,
          "rs_above": false,
          "rs_kpct": -1.8,
          "rs_er": 0.4945,
          "rs_baff": 3,
          "rs_trend": "ROSSO",
          "rs_cross": 15,
          "rs_rsi": 36.5,
          "rs_p7": -1.77,
          "rs_p30": -6.64,
          "rs_ao_pos": false,
          "rs_ao_improving": true,
          "kama_cross_up": false,
          "sec_er": 0.1698,
          "sec_trend": "ROSSO",
          "score": 8.9,
          "signal": "EXIT3",
          "size": "0%",
          "qualifies": false
        },
        {
          "ticker": "WIND.MI",
          "label": "WIND",
          "name": "SPDR MSCI Wld Industrials",
          "price": 80.94,
          "sec_kama": 80.189,
          "sec_above": true,
          "sar": 79.36305,
          "sar_bullish": true,
          "vi_plus": 0.9554,
          "vi_minus": 0.9892,
          "vortex_bullish": false,
          "rvi": -0.152701,
          "rvi_signal": 0.353691,
          "rvi_bullish": false,
          "rs": 1.901562,
          "rs_kama": 1.949941,
          "rs_above": false,
          "rs_kpct": -2.48,
          "rs_er": 0.3236,
          "rs_baff": 0,
          "rs_trend": "ROSSO",
          "rs_cross": 8,
          "rs_rsi": 45.0,
          "rs_p7": -1.78,
          "rs_p30": -1.26,
          "rs_ao_pos": false,
          "rs_ao_improving": false,
          "kama_cross_up": false,
          "sec_er": 0.0306,
          "sec_trend": "VERDE",
          "score": 4.5,
          "signal": "EXIT3",
          "size": "0%",
          "qualifies": false
        },
        {
          "ticker": "WUTI.MI",
          "label": "WUTI",
          "name": "SPDR MSCI Wld Utilities",
          "price": 61.09,
          "sec_kama": 62.0393,
          "sec_above": false,
          "sar": 63.7902,
          "sar_bullish": false,
          "vi_plus": 0.8354,
          "vi_minus": 1.0047,
          "vortex_bullish": false,
          "rvi": -0.31205,
          "rvi_signal": -0.202037,
          "rvi_bullish": false,
          "rs": 1.435217,
          "rs_kama": 1.466178,
          "rs_above": false,
          "rs_kpct": -2.11,
          "rs_er": 0.7263,
          "rs_baff": 0,
          "rs_trend": "GRIGIO",
          "rs_cross": 8,
          "rs_rsi": 36.1,
          "rs_p7": -4.05,
          "rs_p30": -5.01,
          "rs_ao_pos": false,
          "rs_ao_improving": false,
          "kama_cross_up": false,
          "sec_er": 0.5789,
          "sec_trend": "GRIGIO",
          "score": 1.9,
          "signal": "EXIT3",
          "size": "0%",
          "qualifies": false
        },
        {
          "ticker": "WHEA.MI",
          "label": "WHEA",
          "name": "SPDR MSCI Wld Health Care",
          "price": 55.12,
          "sec_kama": 55.6334,
          "sec_above": false,
          "sar": 56.59585,
          "sar_bullish": false,
          "vi_plus": 0.7638,
          "vi_minus": 1.0621,
          "vortex_bullish": false,
          "rvi": -0.23894,
          "rvi_signal": -0.250793,
          "rvi_bullish": true,
          "rs": 1.294961,
          "rs_kama": 1.304531,
          "rs_above": false,
          "rs_kpct": -0.73,
          "rs_er": 0.8541,
          "rs_baff": 0,
          "rs_trend": "ROSSO",
          "rs_cross": 13,
          "rs_rsi": 21.4,
          "rs_p7": -4.0,
          "rs_p30": -7.46,
          "rs_ao_pos": false,
          "rs_ao_improving": false,
          "kama_cross_up": false,
          "sec_er": 0.2997,
          "sec_trend": "ROSSO",
          "score": -1.9,
          "signal": "EXIT3",
          "size": "0%",
          "qualifies": false
        }
      ],
      "qualified": [
        {
          "ticker": "WCOD.MI",
          "label": "WCOD",
          "name": "SPDR MSCI Wld Cons Disc",
          "price": 73.04,
          "sec_kama": 71.9772,
          "sec_above": true,
          "sar": 70.08485,
          "sar_bullish": true,
          "vi_plus": 1.0179,
          "vi_minus": 1.0179,
          "vortex_bullish": false,
          "rvi": 0.799994,
          "rvi_signal": 8.692585,
          "rvi_bullish": false,
          "rs": 1.715964,
          "rs_kama": 1.713207,
          "rs_above": true,
          "rs_kpct": 0.16,
          "rs_er": 0.2137,
          "rs_baff": 7,
          "rs_trend": "GRIGIO",
          "rs_cross": 4,
          "rs_rsi": 52.1,
          "rs_p7": 2.23,
          "rs_p30": 1.94,
          "rs_ao_pos": true,
          "rs_ao_improving": true,
          "kama_cross_up": false,
          "sec_er": 0.5547,
          "sec_trend": "GRIGIO",
          "score": 59.7,
          "signal": "BUY1",
          "size": "30-40%",
          "qualifies": true
        },
        {
          "ticker": "WTEC.MI",
          "label": "WTEC",
          "name": "SPDR MSCI Wld Technology",
          "price": 199.97,
          "sec_kama": 197.368,
          "sec_above": true,
          "sar": 183.58261,
          "sar_bullish": true,
          "vi_plus": 1.2843,
          "vi_minus": 0.5618,
          "vortex_bullish": true,
          "rvi": 0.659345,
          "rvi_signal": 0.463733,
          "rvi_bullish": true,
          "rs": 4.697991,
          "rs_kama": 4.655123,
          "rs_above": true,
          "rs_kpct": 0.92,
          "rs_er": 1.0,
          "rs_baff": 13,
          "rs_trend": "VERDE",
          "rs_cross": 12,
          "rs_rsi": 79.1,
          "rs_p7": 5.1,
          "rs_p30": 6.08,
          "rs_ao_pos": true,
          "rs_ao_improving": true,
          "kama_cross_up": false,
          "sec_er": 0.9494,
          "sec_trend": "VERDE",
          "score": 119.9,
          "signal": "BUY3",
          "size": "100%",
          "qualifies": true
        }
      ],
      "all": [
        {
          "ticker": "WTEC.MI",
          "label": "WTEC",
          "name": "SPDR MSCI Wld Technology",
          "price": 199.97,
          "sec_kama": 197.368,
          "sec_above": true,
          "sar": 183.58261,
          "sar_bullish": true,
          "vi_plus": 1.2843,
          "vi_minus": 0.5618,
          "vortex_bullish": true,
          "rvi": 0.659345,
          "rvi_signal": 0.463733,
          "rvi_bullish": true,
          "rs": 4.697991,
          "rs_kama": 4.655123,
          "rs_above": true,
          "rs_kpct": 0.92,
          "rs_er": 1.0,
          "rs_baff": 13,
          "rs_trend": "VERDE",
          "rs_cross": 12,
          "rs_rsi": 79.1,
          "rs_p7": 5.1,
          "rs_p30": 6.08,
          "rs_ao_pos": true,
          "rs_ao_improving": true,
          "kama_cross_up": false,
          "sec_er": 0.9494,
          "sec_trend": "VERDE",
          "score": 119.9,
          "signal": "BUY3",
          "size": "100%",
          "qualifies": true
        },
        {
          "ticker": "WCOD.MI",
          "label": "WCOD",
          "name": "SPDR MSCI Wld Cons Disc",
          "price": 73.04,
          "sec_kama": 71.9772,
          "sec_above": true,
          "sar": 70.08485,
          "sar_bullish": true,
          "vi_plus": 1.0179,
          "vi_minus": 1.0179,
          "vortex_bullish": false,
          "rvi": 0.799994,
          "rvi_signal": 8.692585,
          "rvi_bullish": false,
          "rs": 1.715964,
          "rs_kama": 1.713207,
          "rs_above": true,
          "rs_kpct": 0.16,
          "rs_er": 0.2137,
          "rs_baff": 7,
          "rs_trend": "GRIGIO",
          "rs_cross": 4,
          "rs_rsi": 52.1,
          "rs_p7": 2.23,
          "rs_p30": 1.94,
          "rs_ao_pos": true,
          "rs_ao_improving": true,
          "kama_cross_up": false,
          "sec_er": 0.5547,
          "sec_trend": "GRIGIO",
          "score": 59.7,
          "signal": "BUY1",
          "size": "30-40%",
          "qualifies": true
        },
        {
          "ticker": "WTEL.MI",
          "label": "WTEL",
          "name": "SPDR MSCI Wld Comm Services",
          "price": 71.5,
          "sec_kama": 71.3685,
          "sec_above": true,
          "sar": 68.78781,
          "sar_bullish": true,
          "vi_plus": 1.3782,
          "vi_minus": 1.2496,
          "vortex_bullish": true,
          "rvi": 1.381731,
          "rvi_signal": 1.610676,
          "rvi_bullish": false,
          "rs": 1.679784,
          "rs_kama": 1.669535,
          "rs_above": true,
          "rs_kpct": 0.61,
          "rs_er": 0.1684,
          "rs_baff": 0,
          "rs_trend": "GRIGIO",
          "rs_cross": 7,
          "rs_rsi": 51.8,
          "rs_p7": 1.48,
          "rs_p30": 0.28,
          "rs_ao_pos": true,
          "rs_ao_improving": false,
          "kama_cross_up": false,
          "sec_er": 0.8177,
          "sec_trend": "VERDE",
          "score": 18.4,
          "signal": "EXIT3",
          "size": "0%",
          "qualifies": false
        },
        {
          "ticker": "WMAT.MI",
          "label": "WMAT",
          "name": "SPDR MSCI Wld Materials",
          "price": 71.65,
          "sec_kama": 71.1188,
          "sec_above": true,
          "sar": 70.67405,
          "sar_bullish": true,
          "vi_plus": 0.7974,
          "vi_minus": 0.6919,
          "vortex_bullish": true,
          "rvi": 0.17771,
          "rvi_signal": 0.084579,
          "rvi_bullish": true,
          "rs": 1.683308,
          "rs_kama": 1.694585,
          "rs_above": false,
          "rs_kpct": -0.67,
          "rs_er": 0.2466,
          "rs_baff": 1,
          "rs_trend": "GRIGIO",
          "rs_cross": 2,
          "rs_rsi": 48.3,
          "rs_p7": -1.68,
          "rs_p30": 2.25,
          "rs_ao_pos": true,
          "rs_ao_improving": true,
          "kama_cross_up": false,
          "sec_er": 0.1353,
          "sec_trend": "VERDE",
          "score": 17.2,
          "signal": "EXIT3",
          "size": "0%",
          "qualifies": false
        },
        {
          "ticker": "WNRG.MI",
          "label": "WNRG",
          "name": "SPDR MSCI Wld Energy",
          "price": 61.1,
          "sec_kama": 62.2981,
          "sec_above": false,
          "sar": 62.89003,
          "sar_bullish": false,
          "vi_plus": 0.8525,
          "vi_minus": 0.9022,
          "vortex_bullish": false,
          "rvi": -0.367062,
          "rvi_signal": -0.339138,
          "rvi_bullish": false,
          "rs": 1.435452,
          "rs_kama": 1.479389,
          "rs_above": false,
          "rs_kpct": -2.97,
          "rs_er": 0.3346,
          "rs_baff": 0,
          "rs_trend": "GRIGIO",
          "rs_cross": 15,
          "rs_rsi": 43.8,
          "rs_p7": -0.92,
          "rs_p30": -0.72,
          "rs_ao_pos": false,
          "rs_ao_improving": false,
          "kama_cross_up": false,
          "sec_er": 0.1729,
          "sec_trend": "GRIGIO",
          "score": 13.8,
          "signal": "EXIT3",
          "size": "0%",
          "qualifies": false
        },
        {
          "ticker": "WFIN.MI",
          "label": "WFIN",
          "name": "SPDR MSCI Wld Financials",
          "price": 80.17,
          "sec_kama": 80.2131,
          "sec_above": false,
          "sar": 78.45473,
          "sar_bullish": true,
          "vi_plus": 1.1729,
          "vi_minus": 1.0404,
          "vortex_bullish": true,
          "rvi": 0.161927,
          "rvi_signal": 0.298476,
          "rvi_bullish": false,
          "rs": 1.883472,
          "rs_kama": 1.905032,
          "rs_above": false,
          "rs_kpct": -1.13,
          "rs_er": 0.255,
          "rs_baff": 0,
          "rs_trend": "ROSSO",
          "rs_cross": 3,
          "rs_rsi": 47.8,
          "rs_p7": -0.35,
          "rs_p30": 2.65,
          "rs_ao_pos": true,
          "rs_ao_improving": false,
          "kama_cross_up": false,
          "sec_er": 0.3896,
          "sec_trend": "VERDE",
          "score": 12.0,
          "signal": "EXIT3",
          "size": "0%",
          "qualifies": false
        },
        {
          "ticker": "WCOS.MI",
          "label": "WCOS",
          "name": "SPDR MSCI Wld Cons Staples",
          "price": 45.535,
          "sec_kama": 45.9778,
          "sec_above": false,
          "sar": 46.28056,
          "sar_bullish": false,
          "vi_plus": 1.0824,
          "vi_minus": 1.5795,
          "vortex_bullish": false,
          "rvi": -1.175051,
          "rvi_signal": -1.300747,
          "rvi_bullish": true,
          "rs": 1.069776,
          "rs_kama": 1.089366,
          "rs_above": false,
          "rs_kpct": -1.8,
          "rs_er": 0.4945,
          "rs_baff": 3,
          "rs_trend": "ROSSO",
          "rs_cross": 15,
          "rs_rsi": 36.5,
          "rs_p7": -1.77,
          "rs_p30": -6.64,
          "rs_ao_pos": false,
          "rs_ao_improving": true,
          "kama_cross_up": false,
          "sec_er": 0.1698,
          "sec_trend": "ROSSO",
          "score": 8.9,
          "signal": "EXIT3",
          "size": "0%",
          "qualifies": false
        },
        {
          "ticker": "WIND.MI",
          "label": "WIND",
          "name": "SPDR MSCI Wld Industrials",
          "price": 80.94,
          "sec_kama": 80.189,
          "sec_above": true,
          "sar": 79.36305,
          "sar_bullish": true,
          "vi_plus": 0.9554,
          "vi_minus": 0.9892,
          "vortex_bullish": false,
          "rvi": -0.152701,
          "rvi_signal": 0.353691,
          "rvi_bullish": false,
          "rs": 1.901562,
          "rs_kama": 1.949941,
          "rs_above": false,
          "rs_kpct": -2.48,
          "rs_er": 0.3236,
          "rs_baff": 0,
          "rs_trend": "ROSSO",
          "rs_cross": 8,
          "rs_rsi": 45.0,
          "rs_p7": -1.78,
          "rs_p30": -1.26,
          "rs_ao_pos": false,
          "rs_ao_improving": false,
          "kama_cross_up": false,
          "sec_er": 0.0306,
          "sec_trend": "VERDE",
          "score": 4.5,
          "signal": "EXIT3",
          "size": "0%",
          "qualifies": false
        },
        {
          "ticker": "WUTI.MI",
          "label": "WUTI",
          "name": "SPDR MSCI Wld Utilities",
          "price": 61.09,
          "sec_kama": 62.0393,
          "sec_above": false,
          "sar": 63.7902,
          "sar_bullish": false,
          "vi_plus": 0.8354,
          "vi_minus": 1.0047,
          "vortex_bullish": false,
          "rvi": -0.31205,
          "rvi_signal": -0.202037,
          "rvi_bullish": false,
          "rs": 1.435217,
          "rs_kama": 1.466178,
          "rs_above": false,
          "rs_kpct": -2.11,
          "rs_er": 0.7263,
          "rs_baff": 0,
          "rs_trend": "GRIGIO",
          "rs_cross": 8,
          "rs_rsi": 36.1,
          "rs_p7": -4.05,
          "rs_p30": -5.01,
          "rs_ao_pos": false,
          "rs_ao_improving": false,
          "kama_cross_up": false,
          "sec_er": 0.5789,
          "sec_trend": "GRIGIO",
          "score": 1.9,
          "signal": "EXIT3",
          "size": "0%",
          "qualifies": false
        },
        {
          "ticker": "WHEA.MI",
          "label": "WHEA",
          "name": "SPDR MSCI Wld Health Care",
          "price": 55.12,
          "sec_kama": 55.6334,
          "sec_above": false,
          "sar": 56.59585,
          "sar_bullish": false,
          "vi_plus": 0.7638,
          "vi_minus": 1.0621,
          "vortex_bullish": false,
          "rvi": -0.23894,
          "rvi_signal": -0.250793,
          "rvi_bullish": true,
          "rs": 1.294961,
          "rs_kama": 1.304531,
          "rs_above": false,
          "rs_kpct": -0.73,
          "rs_er": 0.8541,
          "rs_baff": 0,
          "rs_trend": "ROSSO",
          "rs_cross": 13,
          "rs_rsi": 21.4,
          "rs_p7": -4.0,
          "rs_p30": -7.46,
          "rs_ao_pos": false,
          "rs_ao_improving": false,
          "kama_cross_up": false,
          "sec_er": 0.2997,
          "sec_trend": "ROSSO",
          "score": -1.9,
          "signal": "EXIT3",
          "size": "0%",
          "qualifies": false
        }
      ],
      "buy3_count": 1,
      "buy2_count": 0,
      "buy1_count": 1
    }
  }
}